[{"fields": {"owners": [4, 11], "view_users": [], "short_id": "2cddae40e9594c21b947fdbbe4225439", "creator": 11, "rating_average": 0.0, "rating_sum": 0, "rating_count": 0, "comments_count": 0, "user": 11, "edit_users": [], "public": true}, "model": "hs_model_program.modelprogramresource", "pk": 15}, {"fields": {"owners": [94], "view_users": [], "short_id": "649b0c481ba946a6b25b37c01cdd0acc", "creator": 94, "rating_average": 0.0, "rating_sum": 0, "rating_count": 0, "comments_count": 0, "user": 94, "edit_users": [], "public": true}, "model": "hs_model_program.modelprogramresource", "pk": 198}, {"fields": {"owners": [94], "view_users": [], "short_id": "15254882cb4545b5b101b6081a1d5f01", "creator": 94, "rating_average": 0.0, "rating_sum": 0, "rating_count": 0, "comments_count": 0, "user": 94, "edit_users": [], "public": true}, "model": "hs_model_program.modelprogramresource", "pk": 199}, {"fields": {"owners": [4], "view_users": [], "short_id": "42d142d2cdfb4e92a451ac19c086b903", "creator": 4, "rating_average": 0.0, "rating_sum": 0, "rating_count": 0, "comments_count": 0, "user": 4, "edit_users": [], "public": false}, "model": "hs_model_program.modelprogramresource", "pk": 251}]